Workbook

Sheet Statement of Profit & Loss
A1: EAST INDUSTRIES PRIVATE LIMITED
A2: Statement of Profit & Loss for the year ended 31 March 2026 (FY 2025-26)
A3: Illustrative figures prepared for a portfolio project; amounts in Rs.
A5: Particulars | B5: Amount (Rs.)
A6: Revenue from Operations | B6: 55500000
A7: Other Income | B7: 500000
A8: Total Revenue (A) | B8: =SUM(B6:B7) -> 56000000
A10: Expenses
A11: Cost of Materials Consumed | B11: 17000000
A12: Employee Benefit Expenses | B12: 6500000
A13: Depreciation & Amortization Expense (Companies Act, Schedule II) | B13: 2500000
A14: Finance Costs | B14: 1200000
A15: Corporate Social Responsibility (CSR) Expenditure | B15: 300000
A16: Donation - PM CARES Fund | B16: 250000
A17: Donation - Political Party | B17: 110500
A18: Provision for Doubtful Debts | B18: 533000
A19: Penalty for Late Filing of GST Returns | B19: 70000
A20: Other Administrative & Selling Expenses | B20: 6500000
A21: Total Expenses (B) | B21: =SUM(B11:B20) -> 34963500
A23: Net Profit before Tax (A - B) | B23: =B8-B21 -> 21036500

Sheet Depreciation Schedule
A1: EAST INDUSTRIES PRIVATE LIMITED
A2: Depreciation Schedule as per the Income-tax Act, 1961 (WDV Method, Income-tax Rules, 1962)
A4: Block of Assets | B4: Rate | C4: Opening WDV (1 Apr 2025) Rs. | D4: New assets used for 180 days or more. (Full Depreciation) | E4: New assets used for less than 180 days. (Half Depreciation) | F4: Depreciation Rs.
A5: Plant & Machinery | B5: 0.15 | C5: 14000000 | D5: 2300000 | E5: 1200000 | F5: =(C5+D5)*B5+E5*B5/2 -> 2535000
A6: Furniture & Fixtures | B6: 0.1 | C6: 2500000 | D6: 0 | E6: 0 | F6: =(C6+D6)*B6+E6*B6/2 -> 250000
A7: Computers & Computer Software | B7: 0.4 | C7: 700000 | D7: 0 | E7: 0 | F7: =(C7+D7)*B7+E7*B7/2 -> 280000
A8: Total Depreciation as per Income-tax Act | F8: =SUM(F5:F7) -> 3065000

Sheet Tax Computation
A1: EAST INDUSTRIES PRIVATE LIMITED
A2: Computation of Total Income & Tax Liability - FY 2025-26 (Assessment Year 2026-27)
A3: Domestic company opting for the concessional tax regime under Section 115BAA, Income-tax Act, 1961
A5: Particulars | B5: Amount (Rs.)
A6: Net Profit as per Statement of Profit & Loss | B6: ='Statement of Profit & Loss'!B23 -> 21036500
A8: Add: Inadmissible expenses debited to the Statement of Profit & Loss
A9: Depreciation as per Companies Act | B9: ='Statement of Profit & Loss'!B13 -> 2500000
A10: CSR Expenditure (Disallowed) | B10: ='Statement of Profit & Loss'!B15 -> 300000
A11: Donations debited to P&L (disallowed - see Assumptions & Notes) | B11: ='Statement of Profit & Loss'!B16+'Statement of Profit & Loss'!B17 -> 360500
A12: Provision for Doubtful Debts (disallowed - Section 36(1)(vii)) | B12: ='Statement of Profit & Loss'!B18 -> 533000
A13: Penalty for late filing of GST Return (disallowed - Section 37(1)) | B13: ='Statement of Profit & Loss'!B19 -> 70000
A14: Total Additions (C) | B14: =SUM(B9:B13) -> 3763500
A16: Income before allowing tax depreciation (D = Net Profit + C) | B16: =B6+B14 -> 24800000
A18: Less: Depreciation as per the Income-tax Act (E) | B18: ='Depreciation Schedule'!F8 -> 3065000
A20: Total Income (D - E) | B20: =B16-B18 -> 21735000
A21: Total Income, rounded off (Section 288A) | B21: =ROUND(B20/10,0)*10 -> 21735000
A23: Tax Rate Assumptions
A24: Tax Rate - Section 115BAA | B24: 0.22
A25: Surcharge (flat rate under Section 115BAA) | B25: 0.1
A26: Health & Education Cess | B26: 0.04
A28: Tax on Total Income | B28: =B21*B24 -> 4781700
A29: Add: Surcharge | B29: =B28*B25 -> 478170
A30: Tax + Surcharge | B30: =B28+B29 -> 5259870
A31: Add: Health & Education Cess | B31: =B30*B26 -> 210394.8
A32: Total Tax Liability | B32: =B30+B31 -> 5470264.8
A33: Total Tax Liability, rounded off (Section 288B) | B33: =ROUND(B32/10,0)*10 -> 5470260
A35: Effective Tax Rate (Total Tax Liability / Total Income) | B35: =B33/B21 -> 0.25167978

Sheet Assumptions & Notes
A1: Key Assumptions & Notes
A3: 1. East Industries Private Limited is a fictional company created for a self-study / portfolio project. All figures are illustrative and do not represent any real entity's financial data.
A5: 2. The company is assumed to be a 'domestic company' under the Income-tax Act, 1961, opting for the concessional tax regime under Section 115BAA (22% base rate).
A7: 3. This computation has been prepared in accordance with the Income-tax Act, 1961 and Income-tax Rules, 1962, for FY 2025-26 (Assessment Year 2026-27). Since the cmpany is assumed to be a domestic private limited company subject to statutory audit, the assumed due date for filing the Income Tax Return is 31 October 2026, unless extended bu Government.
A9: 4. Since the company has opted for Section 115BAA, deductions are not available (other than Sections 80JJAA and 80M); donations otherwise eligible under Section 80G have therefore been fully disallowed rather than partly allowed.
A11: 5. CSR expenditure under the Companies Act, 2013 is specifically disallowed as a business deduction under the Income-tax Act, 1961, even though it is a legitimate charge in the Statement of Profit & Loss.
A13: 6. Provision for doubtful debts is disallowed for tax purposes; only actual bad debts written off, subject to the conditions in Section 36(2), are allowable under Section 36(1)(vii) for a non-banking company.
A15: 7. Penalty for late filing of GST returns is disallowed under Section 37(1) as a payment for infraction of law.
A17: 8. Book depreciation is not allowable for tax purposes; depreciation as per the Income-tax Act has been separately computed under the WDV method.
A19: 9. Total Income and Total Tax Liability are rounded off to the nearest Rs. 10 under Sections 288A and 288B respectively.
A21: 10. The 22% base rate, 10% flat surcharge and 4% Health & Education Cess have been stable for several years.
